tufts_dining/__init__.py
tufts_dining/constants.py
tufts_dining/tuftsdining.py
tufts_dining-0.1.0.dist-info/LICENSE
tufts_dining-0.1.0.dist-info/METADATA
tufts_dining-0.1.0.dist-info/WHEEL
tufts_dining-0.1.0.dist-info/top_level.txt
tufts_dining-0.1.0.dist-info/RECORD
